dcc/__init__.py
dcc/dcc.py
dcc/dcc_xml_validator.py
pydcc-0.2.33.dist-info/LICENSE
pydcc-0.2.33.dist-info/METADATA
pydcc-0.2.33.dist-info/WHEEL
pydcc-0.2.33.dist-info/top_level.txt
pydcc-0.2.33.dist-info/RECORD
