Metadata-Version: 2.1
Name: pydcc
Version: 0.2.33
Summary: Library for handling digital calibration certificates (DCC). 
Home-page: https://github.com/siemens/pydcc
Author: Andreas Tobola
Author-email: pydcc.t@siemens.com
License: MIT License
Keywords: digital calibration certificate measurement uncertainty precision GUM DCC
Classifier: Development Status :: 3 - Alpha
Classifier: Topic :: Utilities
Classifier: License :: OSI Approved :: MIT License
Classifier: Programming Language :: Python :: 3
Classifier: Programming Language :: Python :: 3.8
Classifier: Operating System :: OS Independent
License-File: LICENSE
Requires-Dist: xmlschema (>1.5)
Requires-Dist: requests
Requires-Dist: signxml (>=3.1.0)
Requires-Dist: certvalidator
Requires-Dist: asn1crypto
Requires-Dist: cryptography
Requires-Dist: pydantic
